LICENSE
README.md
dtpyfw/__init__.py
dtpyfw/api/__init__.py
dtpyfw/api/application.py
dtpyfw/api/middlewares/__init__.py
dtpyfw/api/middlewares/dealer.py
dtpyfw/api/middlewares/http_exception.py
dtpyfw/api/middlewares/permission.py
dtpyfw/api/middlewares/runtime.py
dtpyfw/api/middlewares/timer.py
dtpyfw/api/middlewares/user.py
dtpyfw/api/middlewares/validation_exception.py
dtpyfw/api/routes/__init__.py
dtpyfw/api/routes/authentication.py
dtpyfw/api/routes/response.py
dtpyfw/api/routes/route.py
dtpyfw/api/routes/router.py
dtpyfw/api/schemas/__init__.py
dtpyfw/api/schemas/filters.py
dtpyfw/api/schemas/models.py
dtpyfw/api/schemas/response.py
dtpyfw/bucket/__init__.py
dtpyfw/bucket/bucket.py
dtpyfw/core/__init__.py
dtpyfw/core/async.py
dtpyfw/core/chunking.py
dtpyfw/core/enums.py
dtpyfw/core/env.py
dtpyfw/core/exception.py
dtpyfw/core/file_folder.py
dtpyfw/core/hashing.py
dtpyfw/core/jsonable_encoder.py
dtpyfw/core/request.py
dtpyfw/core/require_extra.py
dtpyfw/core/retry.py
dtpyfw/core/safe_access.py
dtpyfw/core/singleton.py
dtpyfw/core/slug.py
dtpyfw/core/url.py
dtpyfw/core/validation.py
dtpyfw/db/__init__.py
dtpyfw/db/config.py
dtpyfw/db/database.py
dtpyfw/db/health.py
dtpyfw/db/model.py
dtpyfw/db/schema.py
dtpyfw/db/search.py
dtpyfw/db/search_context.py
dtpyfw/db/search_utils/__init__.py
dtpyfw/db/search_utils/filter_values.py
dtpyfw/db/search_utils/free_search.py
dtpyfw/db/search_utils/make_condition.py
dtpyfw/db/search_utils/selected_filters.py
dtpyfw/db/to_dict.py
dtpyfw/db/utils.py
dtpyfw/encrypt/__init__.py
dtpyfw/encrypt/encryption.py
dtpyfw/encrypt/hashing.py
dtpyfw/ftp/__init__.py
dtpyfw/ftp/client.py
dtpyfw/kafka/__init__.py
dtpyfw/kafka/config.py
dtpyfw/kafka/connection.py
dtpyfw/kafka/consumer.py
dtpyfw/kafka/producer.py
dtpyfw/log/__init__.py
dtpyfw/log/api_handler.py
dtpyfw/log/config.py
dtpyfw/log/footprint.py
dtpyfw/log/formatter.py
dtpyfw/log/handlers.py
dtpyfw/log/initializer.py
dtpyfw/opensearch/__init__.py
dtpyfw/opensearch/client.py
dtpyfw-0.6.24.dist-info/METADATA
dtpyfw-0.6.24.dist-info/WHEEL
dtpyfw-0.6.24.dist-info/licenses/LICENSE
dtpyfw-0.6.24.dist-info/RECORD
