Metadata-Version: 2.4
Name: dtpyfw
Version: 0.6.24
Summary: DealerTower Python Framework: reusable building‑blocks for DealerTower services
License: DealerTower Proprietary License
License-File: LICENSE
Keywords: framework,microservices,fastapi,sqlalchemy,celery,redis,kafka,opensearch
Author: Reza Shirazi
Author-email: reza@dealertower.com
Requires-Python: >=3.11,<4.0
Classifier: Development Status :: 4 - Beta
Classifier: Framework :: Celery
Classifier: Framework :: FastAPI
Classifier: Intended Audience :: Developers
Classifier: License :: Other/Proprietary License
Classifier: Operating System :: OS Independent
Classifier: Programming Language :: Python :: 3
Classifier: Programming Language :: Python :: 3.11
Classifier: Programming Language :: Python :: 3.12
Classifier: Programming Language :: Python :: 3.13
Classifier: Programming Language :: Python :: 3.14
Classifier: Topic :: Software Development :: Libraries :: Application Frameworks
Classifier: Topic :: Software Development :: Libraries :: Python Modules
Classifier: Typing :: Typed
Provides-Extra: all
Provides-Extra: api
Provides-Extra: bucket
Provides-Extra: db
Provides-Extra: db-mysql
Provides-Extra: encrypt
Provides-Extra: ftp
Provides-Extra: kafka
Provides-Extra: normal
Provides-Extra: opensearch
Provides-Extra: redis
Provides-Extra: redis-streamer
Provides-Extra: slim-api
Provides-Extra: slim-task
Provides-Extra: worker
Requires-Dist: PyMySQL (>=1.1.2,<1.2.0) ; extra == "db-mysql"
Requires-Dist: SQLAlchemy (>=2.0.42,<2.1.0) ; extra == "all" or extra == "normal" or extra == "slim-api" or extra == "slim-task" or extra == "db" or extra == "db-mysql"
Requires-Dist: aiomysql (>=0.2.0,<0.3.0) ; extra == "db-mysql"
Requires-Dist: asyncpg (>=0.30.0,<0.31.0) ; extra == "all" or extra == "normal" or extra == "slim-api" or extra == "slim-task" or extra == "db"
Requires-Dist: bcrypt (>=4.3.0,<4.4.0) ; extra == "all" or extra == "encrypt"
Requires-Dist: boto3 (>=1.40.4,<1.41.0) ; extra == "all" or extra == "bucket"
Requires-Dist: celery (>=5.5.3,<5.6.0) ; extra == "all" or extra == "normal" or extra == "slim-task" or extra == "worker"
Requires-Dist: celery-redbeat (>=2.3.3,<2.4.0) ; extra == "all" or extra == "normal" or extra == "slim-task" or extra == "worker"
Requires-Dist: celery_once (>=3.0.1,<3.1.0) ; extra == "all" or extra == "normal" or extra == "slim-task" or extra == "worker"
Requires-Dist: fastapi (>=0.116.1,<0.117.0) ; extra == "all" or extra == "normal" or extra == "slim-api" or extra == "api"
Requires-Dist: gunicorn (>=23.0.0,<23.1.0) ; extra == "all" or extra == "normal" or extra == "slim-api" or extra == "api"
Requires-Dist: kafka-python (>=2.2.15,<2.3.0) ; extra == "all" or extra == "kafka"
Requires-Dist: opensearch-py (>=3.0.0,<3.1.0) ; extra == "all" or extra == "opensearch"
Requires-Dist: paramiko (>=4.0.0,<4.1.0) ; extra == "all" or extra == "ftp"
Requires-Dist: passlib[argon2,bcrypt] (>=1.7.4,<1.8.0) ; extra == "all" or extra == "encrypt"
Requires-Dist: psycopg2 (>=2.9.10,<2.10.0) ; extra == "all" or extra == "normal" or extra == "slim-api" or extra == "slim-task" or extra == "db"
Requires-Dist: pydantic (>=2.11.8,<2.12.0)
Requires-Dist: python-dateutil (>=2.9.0,<2.10.0) ; extra == "all" or extra == "ftp"
Requires-Dist: python-jose (>=3.5.0,<3.6.0) ; extra == "all" or extra == "encrypt"
Requires-Dist: python-multipart (>=0.0.20,<0.1.0) ; extra == "all" or extra == "normal" or extra == "slim-api" or extra == "api"
Requires-Dist: redis (>=6.4.0,<6.5.0) ; extra == "all" or extra == "normal" or extra == "slim-task" or extra == "redis" or extra == "redis-streamer" or extra == "worker"
Requires-Dist: requests (>=2.32.3,<2.33.0)
Requires-Dist: uvicorn (>=0.35.0,<0.36.0) ; extra == "all" or extra == "normal" or extra == "slim-api" or extra == "api"
Project-URL: Documentation, https://github.com/datgate/dtpyfw/tree/main/docs
Project-URL: Homepage, https://github.com/datgate/dtpyfw
Project-URL: Repository, https://github.com/datgate/dtpyfw
